pretix_ga/__init__.py
pretix_ga/apps.py
pretix_ga/signals.py
pretix_ga/urls.py
pretix_ga/views.py
pretix_ga/locale/django.pot
pretix_ga/locale/de/LC_MESSAGES/django.mo
pretix_ga/locale/de/LC_MESSAGES/django.po
pretix_ga/locale/de_Informal/.gitkeep
pretix_ga/locale/de_Informal/LC_MESSAGES/django.mo
pretix_ga/locale/de_Informal/LC_MESSAGES/django.po
pretix_ga/static/pretix_ga/.gitkeep
pretix_ga/templates/pretix_ga/.gitkeep
pretix_ga/templates/pretix_ga/settings.html
pretix_ga-1.2.3.dist-info/LICENSE
pretix_ga-1.2.3.dist-info/METADATA
pretix_ga-1.2.3.dist-info/WHEEL
pretix_ga-1.2.3.dist-info/entry_points.txt
pretix_ga-1.2.3.dist-info/top_level.txt
pretix_ga-1.2.3.dist-info/RECORD
