Metadata-Version: 2.1
Name: pretix-ga
Version: 1.2.3
Summary: Adds Google Analytics capabilities to Pretix
Author-email: Daniel Malik <mail@fronbasal.de>
Maintainer-email: Daniel Malik <mail@fronbasal.de>
License: Apache
Project-URL: homepage, https://github.com/fronbasal/pretix-ga
Project-URL: repository, https://github.com/fronbasal/pretix-ga
Keywords: pretix
License-File: LICENSE
